README.md
setup.py
enocean/__init__.py
enocean/consolelogger.py
enocean/decorators.py
enocean/utils.py
enocean/communicators/__init__.py
enocean/communicators/communicator.py
enocean/communicators/serialcommunicator.py
enocean/communicators/tcpcommunicator.py
enocean/communicators/utils.py
enocean/protocol/EEP.xml
enocean/protocol/__init__.py
enocean/protocol/constants.py
enocean/protocol/crc8.py
enocean/protocol/eep.py
enocean/protocol/packet.py
enocean_lib.egg-info/PKG-INFO
enocean_lib.egg-info/SOURCES.txt
enocean_lib.egg-info/dependency_links.txt
enocean_lib.egg-info/requires.txt
enocean_lib.egg-info/top_level.txt
examples/enocean_example.py