Metadata-Version: 1.0
Name: enocean-lib
Version: 1.0.0
Summary: EnOcean serial protocol implementation (forked from enocean python package)
Home-page: https://github.com/vincentsaluzzo/enocean-lib
Author: Vincent Saluzzo
Author-email: vincentsaluzzo@gmail.com
License: UNKNOWN
Platform: UNKNOWN
